{
    "soleil": {
        "id": "soleil",
        "englishName": "Sun",
        "meanRadius": 695508.0,
        "sideralRotation": 0,
        "axialTilt": 7.25,
        "bodyType": "Star",
        "semimajorAxis": 0,
        "eccentricity": 0,
        "sideralOrbit": 0,
        "inclination": 0,
        "orbitAround": null,
        "longAscNode": 0,
        "argPeriapsis": 0,
        "mainAnomaly": 0,
        "perihelion": 0
    },
    "terre": {
        "id": "terre",
        "englishName": "Earth",
        "meanRadius": 6371.0084,
        "sideralRotation": 23.9345,
        "axialTilt": 23.4393,
        "bodyType": "Planet",
        "semimajorAxis": 149598023,
        "eccentricity": 0.0167,
        "sideralOrbit": 365.256,
        "inclination": 0,
        "orbitAround": "soleil",
        "longAscNode": 18.272,
        "argPeriapsis": 85.901,
        "mainAnomaly": 358.617,
        "perihelion": 147095000
    },
    "lune": {
        "id": "lune",
        "englishName": "Moon",
        "meanRadius": 1737.0,
        "sideralRotation": 655.728,
        "axialTilt": 6.68,
        "bodyType": "Moon",
        "semimajorAxis": 384400,
        "eccentricity": 0.0549,
        "sideralOrbit": 27.3217,
        "inclination": 5.145,
        "orbitAround": "terre",
        "longAscNode": 0,
        "argPeriapsis": 0,
        "mainAnomaly": 0,
        "perihelion": 363300
    },
    "mercure": {
        "id": "mercure",
        "englishName": "Mercury",
        "meanRadius": 2439.4,
        "sideralRotation": 1407.6,
        "axialTilt": 0.0352,
        "bodyType": "Planet",
        "semimajorAxis": 57909050,
        "eccentricity": 0.2056,
        "sideralOrbit": 87.969,
        "inclination": 7.0,
        "orbitAround": "soleil",
        "longAscNode": 48.378,
        "argPeriapsis": 29.022,
        "mainAnomaly": 174.796,
        "perihelion": 46001200
    },
    "venus": {
        "id": "venus",
        "englishName": "Venus",
        "meanRadius": 6051.8,
        "sideralRotation": -5832.5,
        "axialTilt": 177.36,
        "bodyType": "Planet",
        "semimajorAxis": 108208475,
        "eccentricity": 0.0067,
        "sideralOrbit": 224.701,
        "inclination": 3.39,
        "orbitAround": "soleil",
        "longAscNode": 76.785,
        "argPeriapsis": 54.78,
        "mainAnomaly": 50.115,
        "perihelion": 107477000
    },
    "mars": {
        "id": "mars",
        "englishName": "Mars",
        "meanRadius": 3389.5,
        "sideralRotation": 24.6229,
        "axialTilt": 25.19,
        "bodyType": "Planet",
        "semimajorAxis": 227939200,
        "eccentricity": 0.0935,
        "sideralOrbit": 686.98,
        "inclination": 1.85,
        "orbitAround": "soleil",
        "longAscNode": 49.667,
        "argPeriapsis": 286.231,
        "mainAnomaly": 19.412,
        "perihelion": 206700000
    },
    "phobos": {
        "id": "phobos",
        "englishName": "Phobos",
        "meanRadius": 11.1,
        "sideralRotation": 0.7653,
        "axialTilt": 0,
        "bodyType": "Moon",
        "semimajorAxis": 9378,
        "eccentricity": 0.0151,
        "sideralOrbit": 0.31891,
        "inclination": 1.075,
        "orbitAround": "mars",
        "longAscNode": 0,
        "argPeriapsis": 0,
        "mainAnomaly": 0,
        "perihelion": 9234
    },
    "deimos": {
        "id": "deimos",
        "englishName": "Deimos",
        "meanRadius": 6.2,
        "sideralRotation": 30.29856,
        "axialTilt": 0,
        "bodyType": "Moon",
        "semimajorAxis": 23459,
        "eccentricity": 2.0E-4,
        "sideralOrbit": 1.26244,
        "inclination": 1.075,
        "orbitAround": "mars",
        "longAscNode": 0,
        "argPeriapsis": 0,
        "mainAnomaly": 0,
        "perihelion": 23456
    },
    "jupiter": {
        "id": "jupiter",
        "englishName": "Jupiter",
        "meanRadius": 69911.0,
        "sideralRotation": 9.925,
        "axialTilt": 3.12,
        "bodyType": "Planet",
        "semimajorAxis": 778340821,
        "eccentricity": 0.0489,
        "sideralOrbit": 4332.589,
        "inclination": 1.304,
        "orbitAround": "soleil",
        "longAscNode": 100.398,
        "argPeriapsis": 273.442,
        "mainAnomaly": 20.02,
        "perihelion": 740379835
    },
    "io": {
        "id": "io",
        "englishName": "Io",
        "meanRadius": 1821.5,
        "sideralRotation": 42.4593,
        "axialTilt": 0,
        "bodyType": "Moon",
        "semimajorAxis": 421800,
        "eccentricity": 0.004,
        "sideralOrbit": 1.76914,
        "inclination": 0.036,
        "orbitAround": "jupiter",
        "longAscNode": 0,
        "argPeriapsis": 0,
        "mainAnomaly": 0,
        "perihelion": 420071
    },
    "europe": {
        "id": "europe",
        "englishName": "Europa",
        "meanRadius": 1560.8,
        "sideralRotation": 85.2293,
        "axialTilt": 0,
        "bodyType": "Moon",
        "semimajorAxis": 671100,
        "eccentricity": 0.009,
        "sideralOrbit": 3.55118,
        "inclination": 0.466,
        "orbitAround": "jupiter",
        "longAscNode": 0,
        "argPeriapsis": 0,
        "mainAnomaly": 0,
        "perihelion": 0
    },
    "ganymede": {
        "id": "ganymede",
        "englishName": "Ganymede",
        "meanRadius": 2631.2,
        "sideralRotation": 171.7093,
        "axialTilt": 0,
        "bodyType": "Moon",
        "semimajorAxis": 1070400,
        "eccentricity": 0.001,
        "sideralOrbit": 7.15455,
        "inclination": 0.177,
        "orbitAround": "jupiter",
        "longAscNode": 0,
        "argPeriapsis": 0,
        "mainAnomaly": 0,
        "perihelion": 0
    },
    "callisto": {
        "id": "callisto",
        "englishName": "Callisto",
        "meanRadius": 2410.3,
        "sideralRotation": 400.536,
        "axialTilt": 0,
        "bodyType": "Moon",
        "semimajorAxis": 1882700,
        "eccentricity": 0.007,
        "sideralOrbit": 16.68902,
        "inclination": 0.192,
        "orbitAround": "jupiter",
        "longAscNode": 0,
        "argPeriapsis": 0,
        "mainAnomaly": 0,
        "perihelion": 0
    },
    "saturne": {
        "id": "saturne",
        "englishName": "Saturn",
        "meanRadius": 58232.0,
        "sideralRotation": 10.656,
        "axialTilt": 26.73,
        "bodyType": "Planet",
        "semimajorAxis": 1426666422,
        "eccentricity": 0.0565,
        "sideralOrbit": 10759.22,
        "inclination": 2.485,
        "orbitAround": "soleil",
        "longAscNode": 113.759,
        "argPeriapsis": 336.178,
        "mainAnomaly": 317.02,
        "perihelion": 1349823615
    },
    "mimas": {
        "id": "mimas",
        "englishName": "Mimas",
        "meanRadius": 396.4,
        "sideralRotation": 22.56,
        "axialTilt": 0,
        "bodyType": "Moon",
        "semimajorAxis": 185539,
        "eccentricity": 0.0202,
        "sideralOrbit": 0.94,
        "inclination": 1.53,
        "orbitAround": "saturne",
        "longAscNode": 0,
        "argPeriapsis": 0,
        "mainAnomaly": 0,
        "perihelion": 181770
    },
    "encelade": {
        "id": "encelade",
        "englishName": "Enceladus",
        "meanRadius": 504.2,
        "sideralRotation": 32.88,
        "axialTilt": 0,
        "bodyType": "Moon",
        "semimajorAxis": 238042,
        "eccentricity": 0.0045,
        "sideralOrbit": 1.37,
        "inclination": 0,
        "orbitAround": "saturne",
        "longAscNode": 0,
        "argPeriapsis": 0,
        "mainAnomaly": 0,
        "perihelion": 236830
    },
    "tethys": {
        "id": "tethys",
        "englishName": "Tethys",
        "meanRadius": 1066.0,
        "sideralRotation": 45.312,
        "axialTilt": 0,
        "bodyType": "Moon",
        "semimajorAxis": 294672,
        "eccentricity": 1.0E-4,
        "sideralOrbit": 1.89,
        "inclination": 1.86,
        "orbitAround": "saturne",
        "longAscNode": 0,
        "argPeriapsis": 0,
        "mainAnomaly": 0,
        "perihelion": 294589
    },
    "dione": {
        "id": "dione",
        "englishName": "Dione",
        "meanRadius": 1123.4,
        "sideralRotation": 0,
        "axialTilt": 0,
        "bodyType": "Moon",
        "semimajorAxis": 377420,
        "eccentricity": 0.0022,
        "sideralOrbit": 2.737,
        "inclination": 0.002,
        "orbitAround": "saturne",
        "longAscNode": 0,
        "argPeriapsis": 0,
        "mainAnomaly": 0,
        "perihelion": 376580
    },
    "rhea": {
        "id": "rhea",
        "englishName": "Rhea",
        "meanRadius": 1528.6,
        "sideralRotation": 108.432,
        "axialTilt": 0,
        "bodyType": "Moon",
        "semimajorAxis": 527068,
        "eccentricity": 0.001,
        "sideralOrbit": 4.518,
        "inclination": 0.35,
        "orbitAround": "saturne",
        "longAscNode": 0,
        "argPeriapsis": 0,
        "mainAnomaly": 0,
        "perihelion": 526543
    },
    "titan": {
        "id": "titan",
        "englishName": "Titan",
        "meanRadius": 2575.0,
        "sideralRotation": 382.8,
        "axialTilt": 0,
        "bodyType": "Moon",
        "semimajorAxis": 1221865,
        "eccentricity": 0.0292,
        "sideralOrbit": 15.95,
        "inclination": 0.33,
        "orbitAround": "saturne",
        "longAscNode": 0,
        "argPeriapsis": 0,
        "mainAnomaly": 0,
        "perihelion": 1186680
    },
    "hyperion": {
        "id": "hyperion",
        "englishName": "Hyperion",
        "meanRadius": 266.0,
        "sideralRotation": 0,
        "axialTilt": 0,
        "bodyType": "Moon",
        "semimajorAxis": 1500933,
        "eccentricity": 0.123,
        "sideralOrbit": 21.28,
        "inclination": 0.43,
        "orbitAround": "saturne",
        "longAscNode": 0,
        "argPeriapsis": 0,
        "mainAnomaly": 0,
        "perihelion": 1466112
    },
    "japet": {
        "id": "japet",
        "englishName": "Iapetus",
        "meanRadius": 1471.2,
        "sideralRotation": 1735.92,
        "axialTilt": 0,
        "bodyType": "Moon",
        "semimajorAxis": 3560854,
        "eccentricity": 0.0283,
        "sideralOrbit": 79.33,
        "inclination": 14.72,
        "orbitAround": "saturne",
        "longAscNode": 0,
        "argPeriapsis": 0,
        "mainAnomaly": 0,
        "perihelion": 3460068
    },
    "uranus": {
        "id": "uranus",
        "englishName": "Uranus",
        "meanRadius": 25362.0,
        "sideralRotation": -17.24,
        "axialTilt": 97.77,
        "bodyType": "Planet",
        "semimajorAxis": 2870658186,
        "eccentricity": 0.0457,
        "sideralOrbit": 30685.4,
        "inclination": 0.772,
        "orbitAround": "soleil",
        "longAscNode": 73.967,
        "argPeriapsis": 98.862,
        "mainAnomaly": 142.2386,
        "perihelion": 2734998229
    },
    "ariel": {
        "id": "ariel",
        "englishName": "Ariel",
        "meanRadius": 581.1,
        "sideralRotation": 60.4891,
        "axialTilt": 0,
        "bodyType": "Moon",
        "semimajorAxis": 190900,
        "eccentricity": 0.0012,
        "sideralOrbit": 2.52038,
        "inclination": 0.04,
        "orbitAround": "uranus",
        "longAscNode": 0,
        "argPeriapsis": 0,
        "mainAnomaly": 0,
        "perihelion": 190670
    },
    "umbriel": {
        "id": "umbriel",
        "englishName": "Umbriel",
        "meanRadius": 584.7,
        "sideralRotation": 99.499,
        "axialTilt": 0,
        "bodyType": "Moon",
        "semimajorAxis": 266000,
        "eccentricity": 0.0039,
        "sideralOrbit": 4.14418,
        "inclination": 0.13,
        "orbitAround": "uranus",
        "longAscNode": 0,
        "argPeriapsis": 0,
        "mainAnomaly": 0,
        "perihelion": 265100
    },
    "titania": {
        "id": "titania",
        "englishName": "Titania",
        "meanRadius": 788.9,
        "sideralRotation": 208.9408,
        "axialTilt": 0,
        "bodyType": "Moon",
        "semimajorAxis": 436300,
        "eccentricity": 0.0011,
        "sideralOrbit": 8.70587,
        "inclination": 0.08,
        "orbitAround": "uranus",
        "longAscNode": 0,
        "argPeriapsis": 0,
        "mainAnomaly": 0,
        "perihelion": 435800
    },
    "oberon": {
        "id": "oberon",
        "englishName": "Oberon",
        "meanRadius": 761.4,
        "sideralRotation": 323.1176,
        "axialTilt": 0,
        "bodyType": "Moon",
        "semimajorAxis": 583500,
        "eccentricity": 0.0014,
        "sideralOrbit": 13.46323,
        "inclination": 0.07,
        "orbitAround": "uranus",
        "longAscNode": 0,
        "argPeriapsis": 0,
        "mainAnomaly": 0,
        "perihelion": 582702
    },
    "miranda": {
        "id": "miranda",
        "englishName": "Miranda",
        "meanRadius": 240.0,
        "sideralRotation": 33.9235,
        "axialTilt": 0,
        "bodyType": "Moon",
        "semimajorAxis": 129900,
        "eccentricity": 0.0013,
        "sideralOrbit": 1.41348,
        "inclination": 4.34,
        "orbitAround": "uranus",
        "longAscNode": 0,
        "argPeriapsis": 0,
        "mainAnomaly": 0,
        "perihelion": 129703
    },
    "neptune": {
        "id": "neptune",
        "englishName": "Neptune",
        "meanRadius": 24622.0,
        "sideralRotation": 16.11,
        "axialTilt": 28.3,
        "bodyType": "Planet",
        "semimajorAxis": 4498396441,
        "eccentricity": 0.0113,
        "sideralOrbit": 60189.0,
        "inclination": 1.769,
        "orbitAround": "soleil",
        "longAscNode": 131.823,
        "argPeriapsis": 256.932,
        "mainAnomaly": 256.228,
        "perihelion": 4459753056
    },
    "triton": {
        "id": "triton",
        "englishName": "Triton",
        "meanRadius": 1353.4,
        "sideralRotation": 141.0444,
        "axialTilt": 0,
        "bodyType": "Moon",
        "semimajorAxis": 354760,
        "eccentricity": 2.0E-5,
        "sideralOrbit": 5.87685,
        "inclination": 157.345,
        "orbitAround": "neptune",
        "longAscNode": 0,
        "argPeriapsis": 0,
        "mainAnomaly": 0,
        "perihelion": 354753
    }
}